{
    "latitude": 42.3601,
    "longitude": -71.0589,
    "timezone": "America/New_York",
    "currently": {
        "time": 1570751375,
        "summary": "Partly Cloudy",
        "icon": "partly-cloudy-night",
        "nearestStormDistance": 0,
        "precipIntensity": 0,
        "precipProbability": 0,
        "temperature": 55.91,
        "apparentTemperature": 55.91,
        "dewPoint": 41.99,
        "humidity": 0.59,
        "pressure": 1024.38,
        "windSpeed": 13.69,
        "windGust": 15.42,
        "windBearing": 30,
        "cloudCover": 0.42,
        "uvIndex": 0,
        "visibility": 10,
        "ozone": 272
    },
    "minutely": {
        "summary": "Partly cloudy for the hour.",
        "icon": "partly-cloudy-night",
        "data": [
            {
                "time": 1570751340,
                "precipIntensity": 0,
                "precipProbability": 0
            },
            {
                "time": 1570751400,
                "precipIntensity": 0,
                "precipProbability": 0
            },
            {
                "time": 1570751460,
                "precipIntensity": 0,
                "precipProbability": 0
            },
            {
                "time": 1570751520,
                "precipIntensity": 0,
                "precipProbability": 0
            },
            {
                "time": 1570751580,
                "precipIntensity": 0,
                "precipProbability": 0
            },
            {
                "time": 1570751640,
                "precipIntensity": 0,
                "precipProbability": 0
            },
            {
                "time": 1570751700,
                "precipIntensity": 0,
                "precipProbability": 0
            },
            {
                "time": 1570751760,
                "precipIntensity": 0,
                "precipProbability": 0
            },
            {
                "time": 1570751820,
                "precipIntensity": 0,
                "precipProbability": 0
            },
            {
                "time": 1570751880,
                "precipIntensity": 0,
                "precipProbability": 0
            },
            {
                "time": 1570751940,
                "precipIntensity": 0,
                "precipProbability": 0
            },
            {
                "time": 1570752000,
                "precipIntensity": 0,
                "precipProbability": 0
            },
            {
                "time": 1570752060,
                "precipIntensity": 0,
                "precipProbability": 0
            },
            {
                "time": 1570752120,
                "precipIntensity": 0,
                "precipProbability": 0
            },
            {
                "time": 1570752180,
                "precipIntensity": 0,
                "precipProbability": 0
            },
            {
                "time": 1570752240,
                "precipIntensity": 0,
                "precipProbability": 0
            },
            {
                "time": 1570752300,
                "precipIntensity": 0,
                "precipProbability": 0
            },
            {
                "time": 1570752360,
                "precipIntensity": 0,
                "precipProbability": 0
            },
            {
                "time": 1570752420,
                "precipIntensity": 0,
                "precipProbability": 0
            },
            {
                "time": 1570752480,
                "precipIntensity": 0,
                "precipProbability": 0
            },
            {
                "time": 1570752540,
                "precipIntensity": 0,
                "precipProbability": 0
            },
            {
                "time": 1570752600,
                "precipIntensity": 0,
                "precipProbability": 0
            },
            {
                "time": 1570752660,
                "precipIntensity": 0,
                "precipProbability": 0
            },
            {
                "time": 1570752720,
                "precipIntensity": 0,
                "precipProbability": 0
            },
            {
                "time": 1570752780,
                "precipIntensity": 0,
                "precipProbability": 0
            },
            {
                "time": 1570752840,
                "precipIntensity": 0,
                "precipProbability": 0
            },
            {
                "time": 1570752900,
                "precipIntensity": 0,
                "precipProbability": 0
            },
            {
                "time": 1570752960,
                "precipIntensity": 0,
                "precipProbability": 0
            },
            {
                "time": 1570753020,
                "precipIntensity": 0,
                "precipProbability": 0
            },
            {
                "time": 1570753080,
                "precipIntensity": 0,
                "precipProbability": 0
            },
            {
                "time": 1570753140,
                "precipIntensity": 0,
                "precipProbability": 0
            },
            {
                "time": 1570753200,
                "precipIntensity": 0,
                "precipProbability": 0
            },
            {
                "time": 1570753260,
                "precipIntensity": 0,
                "precipProbability": 0
            },
            {
                "time": 1570753320,
                "precipIntensity": 0,
                "precipProbability": 0
            },
            {
                "time": 1570753380,
                "precipIntensity": 0,
                "precipProbability": 0
            },
            {
                "time": 1570753440,
                "precipIntensity": 0,
                "precipProbability": 0
            },
            {
                "time": 1570753500,
                "precipIntensity": 0,
                "precipProbability": 0
            },
            {
                "time": 1570753560,
                "precipIntensity": 0,
                "precipProbability": 0
            },
            {
                "time": 1570753620,
                "precipIntensity": 0,
                "precipProbability": 0
            },
            {
                "time": 1570753680,
                "precipIntensity": 0,
                "precipProbability": 0
            },
            {
                "time": 1570753740,
                "precipIntensity": 0,
                "precipProbability": 0
            },
            {
                "time": 1570753800,
                "precipIntensity": 0,
                "precipProbability": 0
            },
            {
                "time": 1570753860,
                "precipIntensity": 0,
                "precipProbability": 0
            },
            {
                "time": 1570753920,
                "precipIntensity": 0,
                "precipProbability": 0
            },
            {
                "time": 1570753980,
                "precipIntensity": 0,
                "precipProbability": 0
            },
            {
                "time": 1570754040,
                "precipIntensity": 0,
                "precipProbability": 0
            },
            {
                "time": 1570754100,
                "precipIntensity": 0,
                "precipProbability": 0
            },
            {
                "time": 1570754160,
                "precipIntensity": 0,
                "precipProbability": 0
            },
            {
                "time": 1570754220,
                "precipIntensity": 0,
                "precipProbability": 0
            },
            {
                "time": 1570754280,
                "precipIntensity": 0,
                "precipProbability": 0
            },
            {
                "time": 1570754340,
                "precipIntensity": 0,
                "precipProbability": 0
            },
            {
                "time": 1570754400,
                "precipIntensity": 0,
                "precipProbability": 0
            },
            {
                "time": 1570754460,
                "precipIntensity": 0,
                "precipProbability": 0
            },
            {
                "time": 1570754520,
                "precipIntensity": 0,
                "precipProbability": 0
            },
            {
                "time": 1570754580,
                "precipIntensity": 0,
                "precipProbability": 0
            },
            {
                "time": 1570754640,
                "precipIntensity": 0,
                "precipProbability": 0
            },
            {
                "time": 1570754700,
                "precipIntensity": 0,
                "precipProbability": 0
            },
            {
                "time": 1570754760,
                "precipIntensity": 0,
                "precipProbability": 0
            },
            {
                "time": 1570754820,
                "precipIntensity": 0,
                "precipProbability": 0
            },
            {
                "time": 1570754880,
                "precipIntensity": 0,
                "precipProbability": 0
            },
            {
                "time": 1570754940,
                "precipIntensity": 0,
                "precipProbability": 0
            }
        ]
    },
    "hourly": {
        "summary": "Light rain starting tomorrow morning.",
        "icon": "rain",
        "data": [
            {
                "time": 1570748400,
                "summary": "Partly Cloudy",
                "icon": "partly-cloudy-night",
                "precipIntensity": 0,
                "precipProbability": 0,
                "temperature": 55.94,
                "apparentTemperature": 55.94,
                "dewPoint": 41.22,
                "humidity": 0.58,
                "pressure": 1024.56,
                "windSpeed": 13.57,
                "windGust": 14.96,
                "windBearing": 29,
                "cloudCover": 0.45,
                "uvIndex": 0,
                "visibility": 10,
                "ozone": 271.2
            },
            {
                "time": 1570752000,
                "summary": "Partly Cloudy",
                "icon": "partly-cloudy-night",
                "precipIntensity": 0,
                "precipProbability": 0,
                "temperature": 55.9,
                "apparentTemperature": 55.9,
                "dewPoint": 42.21,
                "humidity": 0.6,
                "pressure": 1024.33,
                "windSpeed": 13.72,
                "windGust": 15.62,
                "windBearing": 30,
                "cloudCover": 0.43,
                "uvIndex": 0,
                "visibility": 10,
                "ozone": 272
            },
            {
                "time": 1570755600,
                "summary": "Partly Cloudy",
                "icon": "partly-cloudy-night",
                "precipIntensity": 0.0013,
                "precipProbability": 0.06,
                "precipType": "rain",
                "temperature": 55.8,
                "apparentTemperature": 55.8,
                "dewPoint": 43.13,
                "humidity": 0.62,
                "pressure": 1024.04,
                "windSpeed": 13.94,
                "windGust": 17.08,
                "windBearing": 33,
                "cloudCover": 0.48,
                "uvIndex": 0,
                "visibility": 10,
                "ozone": 272.2
            },
            {
                "time": 1570759200,
                "summary": "Mostly Cloudy",
                "icon": "partly-cloudy-night",
                "precipIntensity": 0,
                "precipProbability": 0,
                "temperature": 56.51,
                "apparentTemperature": 56.51,
                "dewPoint": 44.58,
                "humidity": 0.64,
                "pressure": 1023.92,
                "windSpeed": 16.9,
                "windGust": 27.3,
                "windBearing": 40,
                "cloudCover": 0.76,
                "uvIndex": 0,
                "visibility": 10,
                "ozone": 272.1
            },
            {
                "time": 1570762800,
                "summary": "Mostly Cloudy",
                "icon": "partly-cloudy-night",
                "precipIntensity": 0,
                "precipProbability": 0,
                "temperature": 58.22,
                "apparentTemperature": 58.22,
                "dewPoint": 45.73,
                "humidity": 0.63,
                "pressure": 1023.66,
                "windSpeed": 18.69,
                "windGust": 33.65,
                "windBearing": 42,
                "cloudCover": 0.87,
                "uvIndex": 0,
                "visibility": 10,
                "ozone": 272
            },
            {
                "time": 1570766400,
                "summary": "Overcast",
                "icon": "cloudy",
                "precipIntensity": 0.0007,
                "precipProbability": 0.06,
                "precipType": "rain",
                "temperature": 58.3,
                "apparentTemperature": 58.3,
                "dewPoint": 46.45,
                "humidity": 0.65,
                "pressure": 1023.76,
                "windSpeed": 18.48,
                "windGust": 32.63,
                "windBearing": 45,
                "cloudCover": 0.93,
                "uvIndex": 0,
                "visibility": 10,
                "ozone": 271.9
            },
            {
                "time": 1570770000,
                "summary": "Overcast",
                "icon": "cloudy",
                "precipIntensity": 0.0035,
                "precipProbability": 0.1,
                "precipType": "rain",
                "temperature": 58.18,
                "apparentTemperature": 58.18,
                "dewPoint": 47.13,
                "humidity": 0.67,
                "pressure": 1023.89,
                "windSpeed": 18.26,
                "windGust": 31.82,
                "windBearing": 47,
                "cloudCover": 0.98,
                "uvIndex": 0,
                "visibility": 10,
                "ozone": 271.8
            },
            {
                "time": 1570773600,
                "summary": "Mostly Cloudy",
                "icon": "partly-cloudy-night",
                "precipIntensity": 0.0077,
                "precipProbability": 0.23,
                "precipType": "rain",
                "temperature": 58.07,
                "apparentTemperature": 58.07,
                "dewPoint": 47.76,
                "humidity": 0.68,
                "pressure": 1023.66,
                "windSpeed": 18.27,
                "windGust": 31.47,
                "windBearing": 47,
                "cloudCover": 0.86,
                "uvIndex": 0,
                "visibility": 10,
                "ozone": 272
            },
            {
                "time": 1570777200,
                "summary": "Mostly Cloudy",
                "icon": "partly-cloudy-night",
                "precipIntensity": 0.0132,
                "precipProbability": 0.35,
                "precipType": "rain",
                "temperature": 57.75,
                "apparentTemperature": 57.75,
                "dewPoint": 48.21,
                "humidity": 0.7,
                "pressure": 1023.3,
                "windSpeed": 18.47,
                "windGust": 31.98,
                "windBearing": 44,
                "cloudCover": 0.71,
                "uvIndex": 0,
                "visibility": 10,
                "ozone": 272.5
            },
            {
                "time": 1570780800,
                "summary": "Possible Light Rain",
                "icon": "rain",
                "precipIntensity": 0.0173,
                "precipProbability": 0.39,
                "precipType": "rain",
                "temperature": 56.03,
                "apparentTemperature": 56.03,
                "dewPoint": 48.82,
                "humidity": 0.77,
                "pressure": 1023.05,
                "windSpeed": 18.74,
                "windGust": 32.75,
                "windBearing": 43,
                "cloudCover": 0.8,
                "uvIndex": 0,
                "visibility": 10,
                "ozone": 273.3
            },
            {
                "time": 1570784400,
                "summary": "Possible Light Rain",
                "icon": "rain",
                "precipIntensity": 0.0251,
                "precipProbability": 0.47,
                "precipType": "rain",
                "temperature": 55.45,
                "apparentTemperature": 55.45,
                "dewPoint": 49.28,
                "humidity": 0.8,
                "pressure": 1022.7,
                "windSpeed": 19.2,
                "windGust": 34.74,
                "windBearing": 40,
                "cloudCover": 0.84,
                "uvIndex": 0,
                "visibility": 10,
                "ozone": 274
            },
            {
                "time": 1570788000,
                "summary": "Possible Light Rain",
                "icon": "rain",
                "precipIntensity": 0.0209,
                "precipProbability": 0.44,
                "precipType": "rain",
                "temperature": 54.98,
                "apparentTemperature": 54.98,
                "dewPoint": 49.4,
                "humidity": 0.81,
                "pressure": 1022.74,
                "windSpeed": 19.38,
                "windGust": 35.19,
                "windBearing": 39,
                "cloudCover": 0.84,
                "uvIndex": 0,
                "visibility": 10,
                "ozone": 274.5
            },
            {
                "time": 1570791600,
                "summary": "Possible Light Rain",
                "icon": "rain",
                "precipIntensity": 0.0307,
                "precipProbability": 0.5,
                "precipType": "rain",
                "temperature": 55.01,
                "apparentTemperature": 55.01,
                "dewPoint": 49.62,
                "humidity": 0.82,
                "pressure": 1022.94,
                "windSpeed": 19.48,
                "windGust": 35.2,
                "windBearing": 39,
                "cloudCover": 0.8,
                "uvIndex": 0,
                "visibility": 10,
                "ozone": 275
            },
            {
                "time": 1570795200,
                "summary": "Possible Light Rain",
                "icon": "rain",
                "precipIntensity": 0.018,
                "precipProbability": 0.52,
                "precipType": "rain",
                "temperature": 56.24,
                "apparentTemperature": 56.24,
                "dewPoint": 49.86,
                "humidity": 0.79,
                "pressure": 1022.94,
                "windSpeed": 19.92,
                "windGust": 36.41,
                "windBearing": 38,
                "cloudCover": 0.78,
                "uvIndex": 0,
                "visibility": 10,
                "ozone": 275.4
            },
            {
                "time": 1570798800,
                "summary": "Possible Light Rain",
                "icon": "rain",
                "precipIntensity": 0.0274,
                "precipProbability": 0.62,
                "precipType": "rain",
                "temperature": 55.8,
                "apparentTemperature": 55.8,
                "dewPoint": 50.32,
                "humidity": 0.82,
                "pressure": 1022.98,
                "windSpeed": 20.39,
                "windGust": 35.51,
                "windBearing": 37,
                "cloudCover": 0.87,
                "uvIndex": 1,
                "visibility": 10,
                "ozone": 275.8
            },
            {
                "time": 1570802400,
                "summary": "Possible Light Rain",
                "icon": "rain",
                "precipIntensity": 0.0361,
                "precipProbability": 0.62,
                "precipType": "rain",
                "temperature": 55.14,
                "apparentTemperature": 55.14,
                "dewPoint": 50.2,
                "humidity": 0.83,
                "pressure": 1022.92,
                "windSpeed": 20.57,
                "windGust": 35.65,
                "windBearing": 36,
                "cloudCover": 0.95,
                "uvIndex": 2,
                "visibility": 10,
                "ozone": 276.1
            },
            {
                "time": 1570806000,
                "summary": "Possible Light Rain",
                "icon": "rain",
                "precipIntensity": 0.0419,
                "precipProbability": 0.62,
                "precipType": "rain",
                "temperature": 54.92,
                "apparentTemperature": 54.92,
                "dewPoint": 49.45,
                "humidity": 0.82,
                "pressure": 1022.75,
                "windSpeed": 20.64,
                "windGust": 35.69,
                "windBearing": 35,
                "cloudCover": 1,
                "uvIndex": 3,
                "visibility": 10,
                "ozone": 276.5
            },
            {
                "time": 1570809600,
                "summary": "Possible Light Rain",
                "icon": "rain",
                "precipIntensity": 0.0391,
                "precipProbability": 0.63,
                "precipType": "rain",
                "temperature": 54.31,
                "apparentTemperature": 54.31,
                "dewPoint": 49.38,
                "humidity": 0.83,
                "pressure": 1022.41,
                "windSpeed": 20.55,
                "windGust": 35.71,
                "windBearing": 35,
                "cloudCover": 1,
                "uvIndex": 3,
                "visibility": 10,
                "ozone": 277.2
            },
            {
                "time": 1570813200,
                "summary": "Possible Light Rain",
                "icon": "rain",
                "precipIntensity": 0.0331,
                "precipProbability": 0.65,
                "precipType": "rain",
                "temperature": 53.98,
                "apparentTemperature": 53.98,
                "dewPoint": 49.42,
                "humidity": 0.85,
                "pressure": 1021.99,
                "windSpeed": 20.36,
                "windGust": 35.67,
                "windBearing": 34,
                "cloudCover": 1,
                "uvIndex": 3,
                "visibility": 10,
                "ozone": 277.9
            },
            {
                "time": 1570816800,
                "summary": "Possible Light Rain",
                "icon": "rain",
                "precipIntensity": 0.03,
                "precipProbability": 0.65,
                "precipType": "rain",
                "temperature": 53.84,
                "apparentTemperature": 53.84,
                "dewPoint": 49.34,
                "humidity": 0.85,
                "pressure": 1021.63,
                "windSpeed": 20.18,
                "windGust": 35.56,
                "windBearing": 34,
                "cloudCover": 1,
                "uvIndex": 3,
                "visibility": 10,
                "ozone": 278.9
            },
            {
                "time": 1570820400,
                "summary": "Possible Light Rain",
                "icon": "rain",
                "precipIntensity": 0.0313,
                "precipProbability": 0.65,
                "precipType": "rain",
                "temperature": 54.27,
                "apparentTemperature": 54.27,
                "dewPoint": 48.89,
                "humidity": 0.82,
                "pressure": 1021.46,
                "windSpeed": 20.03,
                "windGust": 35.26,
                "windBearing": 34,
                "cloudCover": 1,
                "uvIndex": 2,
                "visibility": 10,
                "ozone": 280.6
            },
            {
                "time": 1570824000,
                "summary": "Possible Light Rain",
                "icon": "rain",
                "precipIntensity": 0.0345,
                "precipProbability": 0.65,
                "precipType": "rain",
                "temperature": 54.44,
                "apparentTemperature": 54.44,
                "dewPoint": 48.49,
                "humidity": 0.8,
                "pressure": 1021.36,
                "windSpeed": 19.86,
                "windGust": 34.89,
                "windBearing": 35,
                "cloudCover": 1,
                "uvIndex": 1,
                "visibility": 10,
                "ozone": 282.6
            },
            {
                "time": 1570827600,
                "summary": "Possible Light Rain",
                "icon": "rain",
                "precipIntensity": 0.0367,
                "precipProbability": 0.65,
                "precipType": "rain",
                "temperature": 54.75,
                "apparentTemperature": 54.75,
                "dewPoint": 47.94,
                "humidity": 0.78,
                "pressure": 1021.24,
                "windSpeed": 19.76,
                "windGust": 34.65,
                "windBearing": 35,
                "cloudCover": 1,
                "uvIndex": 0,
                "visibility": 10,
                "ozone": 283.9
            },
            {
                "time": 1570831200,
                "summary": "Possible Light Rain",
                "icon": "rain",
                "precipIntensity": 0.0367,
                "precipProbability": 0.63,
                "precipType": "rain",
                "temperature": 54.06,
                "apparentTemperature": 54.06,
                "dewPoint": 47.16,
                "humidity": 0.77,
                "pressure": 1021.08,
                "windSpeed": 19.77,
                "windGust": 34.83,
                "windBearing": 35,
                "cloudCover": 1,
                "uvIndex": 0,
                "visibility": 9.986,
                "ozone": 283.8
            },
            {
                "time": 1570834800,
                "summary": "Possible Light Rain",
                "icon": "rain",
                "precipIntensity": 0.0356,
                "precipProbability": 0.62,
                "precipType": "rain",
                "temperature": 54.3,
                "apparentTemperature": 54.3,
                "dewPoint": 46.81,
                "humidity": 0.76,
                "pressure": 1020.88,
                "windSpeed": 19.82,
                "windGust": 35.14,
                "windBearing": 37,
                "cloudCover": 1,
                "uvIndex": 0,
                "visibility": 9.714,
                "ozone": 283.1
            },
            {
                "time": 1570838400,
                "summary": "Possible Light Rain",
                "icon": "rain",
                "precipIntensity": 0.0328,
                "precipProbability": 0.61,
                "precipType": "rain",
                "temperature": 54.35,
                "apparentTemperature": 54.35,
                "dewPoint": 47.09,
                "humidity": 0.76,
                "pressure": 1020.6,
                "windSpeed": 19.69,
                "windGust": 35.07,
                "windBearing": 38,
                "cloudCover": 1,
                "uvIndex": 0,
                "visibility": 9.979,
                "ozone": 282.5
            },
            {
                "time": 1570842000,
                "summary": "Possible Light Rain",
                "icon": "rain",
                "precipIntensity": 0.0267,
                "precipProbability": 0.58,
                "precipType": "rain",
                "temperature": 54.71,
                "apparentTemperature": 54.71,
                "dewPoint": 47.61,
                "humidity": 0.77,
                "pressure": 1020.14,
                "windSpeed": 19.21,
                "windGust": 34.26,
                "windBearing": 38,
                "cloudCover": 1,
                "uvIndex": 0,
                "visibility": 10,
                "ozone": 282.6
            },
            {
                "time": 1570845600,
                "summary": "Possible Light Rain",
                "icon": "rain",
                "precipIntensity": 0.0202,
                "precipProbability": 0.53,
                "precipType": "rain",
                "temperature": 55.29,
                "apparentTemperature": 55.29,
                "dewPoint": 47.75,
                "humidity": 0.76,
                "pressure": 1019.61,
                "windSpeed": 18.55,
                "windGust": 33.04,
                "windBearing": 38,
                "cloudCover": 1,
                "uvIndex": 0,
                "visibility": 10,
                "ozone": 282.8
            },
            {
                "time": 1570849200,
                "summary": "Possible Light Rain",
                "icon": "rain",
                "precipIntensity": 0.0167,
                "precipProbability": 0.46,
                "precipType": "rain",
                "temperature": 55.83,
                "apparentTemperature": 55.83,
                "dewPoint": 47.99,
                "humidity": 0.75,
                "pressure": 1019.05,
                "windSpeed": 17.9,
                "windGust": 31.96,
                "windBearing": 37,
                "cloudCover": 1,
                "uvIndex": 0,
                "visibility": 10,
                "ozone": 282.5
            },
            {
                "time": 1570852800,
                "summary": "Possible Drizzle",
                "icon": "rain",
                "precipIntensity": 0.0153,
                "precipProbability": 0.41,
                "precipType": "rain",
                "temperature": 56.09,
                "apparentTemperature": 56.09,
                "dewPoint": 48.14,
                "humidity": 0.75,
                "pressure": 1018.39,
                "windSpeed": 17.32,
                "windGust": 31.2,
                "windBearing": 35,
                "cloudCover": 1,
                "uvIndex": 0,
                "visibility": 10,
                "ozone": 281.3
            },
            {
                "time": 1570856400,
                "summary": "Overcast",
                "icon": "cloudy",
                "precipIntensity": 0.0152,
                "precipProbability": 0.37,
                "precipType": "rain",
                "temperature": 56.06,
                "apparentTemperature": 56.06,
                "dewPoint": 48.27,
                "humidity": 0.75,
                "pressure": 1017.71,
                "windSpeed": 16.78,
                "windGust": 30.58,
                "windBearing": 34,
                "cloudCover": 1,
                "uvIndex": 0,
                "visibility": 10,
                "ozone": 279.5
            },
            {
                "time": 1570860000,
                "summary": "Overcast",
                "icon": "cloudy",
                "precipIntensity": 0.0152,
                "precipProbability": 0.34,
                "precipType": "rain",
                "temperature": 55.89,
                "apparentTemperature": 55.89,
                "dewPoint": 48.48,
                "humidity": 0.76,
                "pressure": 1017.13,
                "windSpeed": 16.35,
                "windGust": 30.17,
                "windBearing": 31,
                "cloudCover": 1,
                "uvIndex": 0,
                "visibility": 10,
                "ozone": 277.7
            },
            {
                "time": 1570863600,
                "summary": "Overcast",
                "icon": "cloudy",
                "precipIntensity": 0.0145,
                "precipProbability": 0.34,
                "precipType": "rain",
                "temperature": 55.74,
                "apparentTemperature": 55.74,
                "dewPoint": 48.69,
                "humidity": 0.77,
                "pressure": 1016.73,
                "windSpeed": 16.1,
                "windGust": 30.04,
                "windBearing": 30,
                "cloudCover": 1,
                "uvIndex": 0,
                "visibility": 10,
                "ozone": 276
            },
            {
                "time": 1570867200,
                "summary": "Overcast",
                "icon": "cloudy",
                "precipIntensity": 0.0141,
                "precipProbability": 0.34,
                "precipType": "rain",
                "temperature": 55.6,
                "apparentTemperature": 55.6,
                "dewPoint": 48.86,
                "humidity": 0.78,
                "pressure": 1016.42,
                "windSpeed": 15.95,
                "windGust": 30.13,
                "windBearing": 28,
                "cloudCover": 1,
                "uvIndex": 0,
                "visibility": 10,
                "ozone": 274.3
            },
            {
                "time": 1570870800,
                "summary": "Overcast",
                "icon": "cloudy",
                "precipIntensity": 0.0149,
                "precipProbability": 0.34,
                "precipType": "rain",
                "temperature": 55.2,
                "apparentTemperature": 55.2,
                "dewPoint": 49.08,
                "humidity": 0.8,
                "pressure": 1016.17,
                "windSpeed": 15.75,
                "windGust": 30.14,
                "windBearing": 27,
                "cloudCover": 1,
                "uvIndex": 0,
                "visibility": 10,
                "ozone": 272.8
            },
            {
                "time": 1570874400,
                "summary": "Overcast",
                "icon": "cloudy",
                "precipIntensity": 0.0191,
                "precipProbability": 0.35,
                "precipType": "rain",
                "temperature": 54.78,
                "apparentTemperature": 54.78,
                "dewPoint": 49.52,
                "humidity": 0.82,
                "pressure": 1015.98,
                "windSpeed": 15.45,
                "windGust": 30.24,
                "windBearing": 25,
                "cloudCover": 1,
                "uvIndex": 0,
                "visibility": 10,
                "ozone": 271.5
            },
            {
                "time": 1570878000,
                "summary": "Overcast",
                "icon": "cloudy",
                "precipIntensity": 0.0278,
                "precipProbability": 0.37,
                "precipType": "rain",
                "temperature": 54.59,
                "apparentTemperature": 54.59,
                "dewPoint": 49.76,
                "humidity": 0.84,
                "pressure": 1015.85,
                "windSpeed": 15.1,
                "windGust": 30.25,
                "windBearing": 24,
                "cloudCover": 1,
                "uvIndex": 0,
                "visibility": 10,
                "ozone": 270.4
            },
            {
                "time": 1570881600,
                "summary": "Overcast",
                "icon": "cloudy",
                "precipIntensity": 0.0328,
                "precipProbability": 0.36,
                "precipType": "rain",
                "temperature": 55.73,
                "apparentTemperature": 55.73,
                "dewPoint": 49.8,
                "humidity": 0.8,
                "pressure": 1015.72,
                "windSpeed": 14.6,
                "windGust": 29.71,
                "windBearing": 23,
                "cloudCover": 1,
                "uvIndex": 0,
                "visibility": 10,
                "ozone": 269.4
            },
            {
                "time": 1570885200,
                "summary": "Overcast",
                "icon": "cloudy",
                "precipIntensity": 0.0255,
                "precipProbability": 0.36,
                "precipType": "rain",
                "temperature": 55.2,
                "apparentTemperature": 55.2,
                "dewPoint": 49.83,
                "humidity": 0.82,
                "pressure": 1015.61,
                "windSpeed": 13.99,
                "windGust": 28.26,
                "windBearing": 22,
                "cloudCover": 1,
                "uvIndex": 1,
                "visibility": 10,
                "ozone": 268.7
            },
            {
                "time": 1570888800,
                "summary": "Overcast",
                "icon": "cloudy",
                "precipIntensity": 0.0164,
                "precipProbability": 0.33,
                "precipType": "rain",
                "temperature": 54.94,
                "apparentTemperature": 54.94,
                "dewPoint": 49.27,
                "humidity": 0.81,
                "pressure": 1015.52,
                "windSpeed": 13.25,
                "windGust": 26.3,
                "windBearing": 20,
                "cloudCover": 1,
                "uvIndex": 2,
                "visibility": 10,
                "ozone": 268.2
            },
            {
                "time": 1570892400,
                "summary": "Overcast",
                "icon": "cloudy",
                "precipIntensity": 0.0117,
                "precipProbability": 0.26,
                "precipType": "rain",
                "temperature": 54.9,
                "apparentTemperature": 54.9,
                "dewPoint": 49.38,
                "humidity": 0.82,
                "pressure": 1015.37,
                "windSpeed": 12.49,
                "windGust": 24.29,
                "windBearing": 19,
                "cloudCover": 1,
                "uvIndex": 3,
                "visibility": 10,
                "ozone": 267.3
            },
            {
                "time": 1570896000,
                "summary": "Overcast",
                "icon": "cloudy",
                "precipIntensity": 0.0073,
                "precipProbability": 0.19,
                "precipType": "rain",
                "temperature": 54.97,
                "apparentTemperature": 54.97,
                "dewPoint": 49.48,
                "humidity": 0.82,
                "pressure": 1015.17,
                "windSpeed": 11.71,
                "windGust": 22.33,
                "windBearing": 17,
                "cloudCover": 1,
                "uvIndex": 3,
                "visibility": 10,
                "ozone": 265.9
            },
            {
                "time": 1570899600,
                "summary": "Overcast",
                "icon": "cloudy",
                "precipIntensity": 0.0037,
                "precipProbability": 0.12,
                "precipType": "rain",
                "temperature": 55.24,
                "apparentTemperature": 55.24,
                "dewPoint": 49.33,
                "humidity": 0.8,
                "pressure": 1014.89,
                "windSpeed": 10.89,
                "windGust": 20.3,
                "windBearing": 14,
                "cloudCover": 1,
                "uvIndex": 3,
                "visibility": 10,
                "ozone": 264.2
            },
            {
                "time": 1570903200,
                "summary": "Overcast",
                "icon": "cloudy",
                "precipIntensity": 0.0025,
                "precipProbability": 0.08,
                "precipType": "rain",
                "temperature": 55.29,
                "apparentTemperature": 55.29,
                "dewPoint": 49,
                "humidity": 0.79,
                "pressure": 1014.66,
                "windSpeed": 10.04,
                "windGust": 18.36,
                "windBearing": 11,
                "cloudCover": 1,
                "uvIndex": 3,
                "visibility": 10,
                "ozone": 262.8
            },
            {
                "time": 1570906800,
                "summary": "Overcast",
                "icon": "cloudy",
                "precipIntensity": 0.0019,
                "precipProbability": 0.06,
                "precipType": "rain",
                "temperature": 55.54,
                "apparentTemperature": 55.54,
                "dewPoint": 48.41,
                "humidity": 0.77,
                "pressure": 1014.46,
                "windSpeed": 9.14,
                "windGust": 16.5,
                "windBearing": 11,
                "cloudCover": 1,
                "uvIndex": 2,
                "visibility": 10,
                "ozone": 261.9
            },
            {
                "time": 1570910400,
                "summary": "Overcast",
                "icon": "cloudy",
                "precipIntensity": 0.0017,
                "precipProbability": 0.05,
                "precipType": "rain",
                "temperature": 55.5,
                "apparentTemperature": 55.5,
                "dewPoint": 47.76,
                "humidity": 0.75,
                "pressure": 1014.3,
                "windSpeed": 8.24,
                "windGust": 14.69,
                "windBearing": 9,
                "cloudCover": 1,
                "uvIndex": 1,
                "visibility": 10,
                "ozone": 261.3
            },
            {
                "time": 1570914000,
                "summary": "Overcast",
                "icon": "cloudy",
                "precipIntensity": 0.0016,
                "precipProbability": 0.04,
                "precipType": "rain",
                "temperature": 55.35,
                "apparentTemperature": 55.35,
                "dewPoint": 47.15,
                "humidity": 0.74,
                "pressure": 1014.24,
                "windSpeed": 7.43,
                "windGust": 13.11,
                "windBearing": 7,
                "cloudCover": 1,
                "uvIndex": 0,
                "visibility": 10,
                "ozone": 261.5
            },
            {
                "time": 1570917600,
                "summary": "Overcast",
                "icon": "cloudy",
                "precipIntensity": 0.001,
                "precipProbability": 0.03,
                "precipType": "rain",
                "temperature": 55.4,
                "apparentTemperature": 55.4,
                "dewPoint": 46.29,
                "humidity": 0.71,
                "pressure": 1014.32,
                "windSpeed": 6.8,
                "windGust": 11.78,
                "windBearing": 1,
                "cloudCover": 0.98,
                "uvIndex": 0,
                "visibility": 10,
                "ozone": 262.8
            },
            {
                "time": 1570921200,
                "summary": "Overcast",
                "icon": "cloudy",
                "precipIntensity": 0.0004,
                "precipProbability": 0.02,
                "precipType": "rain",
                "temperature": 54.47,
                "apparentTemperature": 54.47,
                "dewPoint": 45.23,
                "humidity": 0.71,
                "pressure": 1014.4,
                "windSpeed": 6.28,
                "windGust": 10.64,
                "windBearing": 350,
                "cloudCover": 0.95,
                "uvIndex": 0,
                "visibility": 10,
                "ozone": 264.7
            }
        ]
    },
    "daily": {
        "summary": "Light rain throughout the week, with high temperatures bottoming out at 56°F on Saturday.",
        "icon": "rain",
        "data": [
            {
                "time": 1570680000,
                "summary": "Possible light rain in the morning.",
                "icon": "rain",
                "sunriseTime": 1570704744,
                "sunsetTime": 1570745539,
                "moonPhase": 0.41,
                "precipIntensity": 0.0014,
                "precipIntensityMax": 0.0044,
                "precipIntensityMaxTime": 1570719600,
                "precipProbability": 0.84,
                "precipType": "rain",
                "temperatureHigh": 56.61,
                "temperatureHighTime": 1570748400,
                "temperatureLow": 54.33,
                "temperatureLowTime": 1570788000,
                "apparentTemperatureHigh": 55.94,
                "apparentTemperatureHighTime": 1570748400,
                "apparentTemperatureLow": 54.98,
                "apparentTemperatureLowTime": 1570788000,
                "dewPoint": 44.79,
                "humidity": 0.7,
                "pressure": 1024.82,
                "windSpeed": 12.94,
                "windGust": 33.65,
                "windGustTime": 1570762800,
                "windBearing": 26,
                "cloudCover": 0.83,
                "uvIndex": 3,
                "uvIndexTime": 1570723200,
                "visibility": 9.784,
                "ozone": 272.5,
                "temperatureMin": 51.78,
                "temperatureMinTime": 1570705200,
                "temperatureMax": 58.97,
                "temperatureMaxTime": 1570766400,
                "apparentTemperatureMin": 52.43,
                "apparentTemperatureMinTime": 1570705200,
                "apparentTemperatureMax": 58.3,
                "apparentTemperatureMaxTime": 1570766400
            },
            {
                "time": 1570766400,
                "summary": "Light rain throughout the day.",
                "icon": "rain",
                "sunriseTime": 1570791212,
                "sunsetTime": 1570831839,
                "moonPhase": 0.44,
                "precipIntensity": 0.0253,
                "precipIntensityMax": 0.0419,
                "precipIntensityMaxTime": 1570806000,
                "precipProbability": 0.97,
                "precipType": "rain",
                "temperatureHigh": 56.91,
                "temperatureHighTime": 1570795200,
                "temperatureLow": 53.65,
                "temperatureLowTime": 1570834800,
                "apparentTemperatureHigh": 56.24,
                "apparentTemperatureHighTime": 1570795200,
                "apparentTemperatureLow": 54.3,
                "apparentTemperatureLowTime": 1570834800,
                "dewPoint": 48.5,
                "humidity": 0.78,
                "pressure": 1021.9,
                "windSpeed": 19.39,
                "windGust": 36.41,
                "windGustTime": 1570795200,
                "windBearing": 38,
                "cloudCover": 0.93,
                "uvIndex": 3,
                "uvIndexTime": 1570809600,
                "visibility": 9.987,
                "ozone": 277.9,
                "temperatureMin": 53.19,
                "temperatureMinTime": 1570816800,
                "temperatureMax": 58.97,
                "temperatureMaxTime": 1570766400,
                "apparentTemperatureMin": 53.84,
                "apparentTemperatureMinTime": 1570816800,
                "apparentTemperatureMax": 58.3,
                "apparentTemperatureMaxTime": 1570766400
            },
            {
                "time": 1570852800,
                "summary": "Possible light rain in the morning.",
                "icon": "rain",
                "sunriseTime": 1570877680,
                "sunsetTime": 1570918140,
                "moonPhase": 0.47,
                "precipIntensity": 0.0098,
                "precipIntensityMax": 0.0328,
                "precipIntensityMaxTime": 1570881600,
                "precipProbability": 0.78,
                "precipType": "rain",
                "temperatureHigh": 56.4,
                "temperatureHighTime": 1570881600,
                "temperatureLow": 51.94,
                "temperatureLowTime": 1570946400,
                "apparentTemperatureHigh": 55.73,
                "apparentTemperatureHighTime": 1570881600,
                "apparentTemperatureLow": 52.59,
                "apparentTemperatureLowTime": 1570946400,
                "dewPoint": 47.87,
                "humidity": 0.77,
                "pressure": 1015.43,
                "windSpeed": 11.23,
                "windGust": 31.2,
                "windGustTime": 1570852800,
                "windBearing": 17,
                "cloudCover": 0.95,
                "uvIndex": 3,
                "uvIndexTime": 1570899600,
                "visibility": 10,
                "ozone": 268.6,
                "temperatureMin": 52.46,
                "temperatureMinTime": 1570939200,
                "temperatureMax": 56.76,
                "temperatureMaxTime": 1570852800,
                "apparentTemperatureMin": 53.11,
                "apparentTemperatureMinTime": 1570939200,
                "apparentTemperatureMax": 56.09,
                "apparentTemperatureMaxTime": 1570852800
            },
            {
                "time": 1570939200,
                "summary": "Possible light rain in the morning and overnight.",
                "icon": "partly-cloudy-day",
                "sunriseTime": 1570964149,
                "sunsetTime": 1571004442,
                "moonPhase": 0.51,
                "precipIntensity": 0.0002,
                "precipIntensityMax": 0.0014,
                "precipIntensityMaxTime": 1571025600,
                "precipProbability": 0.12,
                "precipType": "rain",
                "temperatureHigh": 68.21,
                "temperatureHighTime": 1570993200,
                "temperatureLow": 45.69,
                "temperatureLowTime": 1571050800,
                "apparentTemperatureHigh": 67.54,
                "apparentTemperatureHighTime": 1570993200,
                "apparentTemperatureLow": 45.91,
                "apparentTemperatureLowTime": 1571047200,
                "dewPoint": 47.24,
                "humidity": 0.66,
                "pressure": 1015.79,
                "windSpeed": 5.57,
                "windGust": 12.96,
                "windGustTime": 1570971600,
                "windBearing": 280,
                "cloudCover": 0.62,
                "uvIndex": 4,
                "uvIndexTime": 1570982400,
                "visibility": 10,
                "ozone": 272,
                "temperatureMin": 51.94,
                "temperatureMinTime": 1570946400,
                "temperatureMax": 68.21,
                "temperatureMaxTime": 1570993200,
                "apparentTemperatureMin": 52.59,
                "apparentTemperatureMinTime": 1570946400,
                "apparentTemperatureMax": 67.54,
                "apparentTemperatureMaxTime": 1570993200
            },
            {
                "time": 1571025600,
                "summary": "Light rain in the morning.",
                "icon": "rain",
                "sunriseTime": 1571050618,
                "sunsetTime": 1571090744,
                "moonPhase": 0.54,
                "precipIntensity": 0.0102,
                "precipIntensityMax": 0.0613,
                "precipIntensityMaxTime": 1571040000,
                "precipProbability": 0.79,
                "precipType": "rain",
                "temperatureHigh": 69.97,
                "temperatureHighTime": 1571079600,
                "temperatureLow": 47.7,
                "temperatureLowTime": 1571137200,
                "apparentTemperatureHigh": 69.3,
                "apparentTemperatureHighTime": 1571079600,
                "apparentTemperatureLow": 46.22,
                "apparentTemperatureLowTime": 1571137200,
                "dewPoint": 45.59,
                "humidity": 0.63,
                "pressure": 1014.85,
                "windSpeed": 5.47,
                "windGust": 21.34,
                "windGustTime": 1571104800,
                "windBearing": 202,
                "cloudCover": 0.52,
                "uvIndex": 4,
                "uvIndexTime": 1571072400,
                "visibility": 9.812,
                "ozone": 281.3,
                "temperatureMin": 45.69,
                "temperatureMinTime": 1571050800,
                "temperatureMax": 69.97,
                "temperatureMaxTime": 1571079600,
                "apparentTemperatureMin": 45.91,
                "apparentTemperatureMinTime": 1571047200,
                "apparentTemperatureMax": 69.3,
                "apparentTemperatureMaxTime": 1571079600
            },
            {
                "time": 1571112000,
                "summary": "Mostly cloudy throughout the day.",
                "icon": "partly-cloudy-day",
                "sunriseTime": 1571137087,
                "sunsetTime": 1571177047,
                "moonPhase": 0.57,
                "precipIntensity": 0,
                "precipIntensityMax": 0.0002,
                "precipIntensityMaxTime": 1571173200,
                "precipProbability": 0.03,
                "temperatureHigh": 64.27,
                "temperatureHighTime": 1571166000,
                "temperatureLow": 53.12,
                "temperatureLowTime": 1571202000,
                "apparentTemperatureHigh": 63.6,
                "apparentTemperatureHighTime": 1571166000,
                "apparentTemperatureLow": 53.77,
                "apparentTemperatureLowTime": 1571202000,
                "dewPoint": 39.04,
                "humidity": 0.53,
                "pressure": 1018.36,
                "windSpeed": 5.71,
                "windGust": 19.94,
                "windGustTime": 1571112000,
                "windBearing": 228,
                "cloudCover": 0.56,
                "uvIndex": 3,
                "uvIndexTime": 1571158800,
                "visibility": 10,
                "ozone": 290.7,
                "temperatureMin": 47.7,
                "temperatureMinTime": 1571137200,
                "temperatureMax": 64.27,
                "temperatureMaxTime": 1571166000,
                "apparentTemperatureMin": 46.22,
                "apparentTemperatureMinTime": 1571137200,
                "apparentTemperatureMax": 63.6,
                "apparentTemperatureMaxTime": 1571166000
            },
            {
                "time": 1571198400,
                "summary": "Light rain throughout the day.",
                "icon": "rain",
                "sunriseTime": 1571223557,
                "sunsetTime": 1571263351,
                "moonPhase": 0.6,
                "precipIntensity": 0.0248,
                "precipIntensityMax": 0.0697,
                "precipIntensityMaxTime": 1571281200,
                "precipProbability": 0.94,
                "precipType": "rain",
                "temperatureHigh": 69.59,
                "temperatureHighTime": 1571252400,
                "temperatureLow": 48.54,
                "temperatureLowTime": 1571310000,
                "apparentTemperatureHigh": 68.92,
                "apparentTemperatureHighTime": 1571252400,
                "apparentTemperatureLow": 44.5,
                "apparentTemperatureLowTime": 1571310000,
                "dewPoint": 48.52,
                "humidity": 0.63,
                "pressure": 1007.87,
                "windSpeed": 9.28,
                "windGust": 31.57,
                "windGustTime": 1571263200,
                "windBearing": 176,
                "cloudCover": 0.8,
                "uvIndex": 3,
                "uvIndexTime": 1571241600,
                "visibility": 8.777,
                "ozone": 303.7,
                "temperatureMin": 53.12,
                "temperatureMinTime": 1571202000,
                "temperatureMax": 69.59,
                "temperatureMaxTime": 1571252400,
                "apparentTemperatureMin": 53.77,
                "apparentTemperatureMinTime": 1571202000,
                "apparentTemperatureMax": 68.92,
                "apparentTemperatureMaxTime": 1571252400
            },
            {
                "time": 1571284800,
                "summary": "Partly cloudy throughout the day.",
                "icon": "rain",
                "sunriseTime": 1571310027,
                "sunsetTime": 1571349656,
                "moonPhase": 0.63,
                "precipIntensity": 0.0039,
                "precipIntensityMax": 0.0529,
                "precipIntensityMaxTime": 1571284800,
                "precipProbability": 0.74,
                "precipType": "rain",
                "temperatureHigh": 58.78,
                "temperatureHighTime": 1571342400,
                "temperatureLow": 44.34,
                "temperatureLowTime": 1571396400,
                "apparentTemperatureHigh": 58.11,
                "apparentTemperatureHighTime": 1571342400,
                "apparentTemperatureLow": 41.27,
                "apparentTemperatureLowTime": 1571396400,
                "dewPoint": 35.33,
                "humidity": 0.5,
                "pressure": 1005.57,
                "windSpeed": 11.24,
                "windGust": 29.65,
                "windGustTime": 1571328000,
                "windBearing": 285,
                "cloudCover": 0.4,
                "uvIndex": 3,
                "uvIndexTime": 1571328000,
                "visibility": 9.958,
                "ozone": 336,
                "temperatureMin": 47.46,
                "temperatureMinTime": 1571371200,
                "temperatureMax": 58.78,
                "temperatureMaxTime": 1571342400,
                "apparentTemperatureMin": 44.5,
                "apparentTemperatureMinTime": 1571310000,
                "apparentTemperatureMax": 58.11,
                "apparentTemperatureMaxTime": 1571342400
            }
        ]
    },
    "flags": {
        "sources": [
            "nwspa",
            "cmc",
            "gfs",
            "hrrr",
            "icon",
            "isd",
            "madis",
            "nam",
            "sref",
            "darksky",
            "nearest-precip"
        ],
        "nearest-station": 0.462,
        "units": "us"
    },
    "offset": -4
}
